celeste_bfl/__init__.py
celeste_bfl/py.typed
celeste_bfl/images/__init__.py
celeste_bfl/images/client.py
celeste_bfl/images/config.py
celeste_bfl/images/parameters.py
celeste_bfl/images/utils.py
celeste_bfl-0.3.6.dist-info/METADATA
celeste_bfl-0.3.6.dist-info/WHEEL
celeste_bfl-0.3.6.dist-info/RECORD
